Metadata-Version: 2.1
Name: tarvis-exchange-dydx
Version: 0.9.11
Summary: Tarvis Exchange Library for dYdX
Home-page: https://tarvislabs.com/
Author: Tarvis Labs
Author-email: python@tarvislabs.com
License: MIT
Platform: UNKNOWN
Classifier: License :: OSI Approved :: MIT License
Requires-Python: >=3.10
License-File: LICENSE.txt
Requires-Dist: dydx-v3-python (==1.9.1)
Requires-Dist: requests (==2.28.1)
Requires-Dist: tarvis-common (==0.9.11)
